adafruit_max31856.py
adafruit_circuitpython_max31856-0.12.5.dist-info/licenses/LICENSE
adafruit_circuitpython_max31856-0.12.5.dist-info/METADATA
adafruit_circuitpython_max31856-0.12.5.dist-info/WHEEL
adafruit_circuitpython_max31856-0.12.5.dist-info/top_level.txt
adafruit_circuitpython_max31856-0.12.5.dist-info/RECORD
