Metadata-Version: 2.4
Name: adafruit-circuitpython-max31856
Version: 0.12.5
Summary: CircuitPython library for the MAX31856 Universal Thermocouple Amplifier.
Author-email: Adafruit Industries <circuitpython@adafruit.com>
License: MIT
Project-URL: Homepage, https://github.com/adafruit/Adafruit_CircuitPython_MAX31856
Keywords: adafruit,max31856,universal,thermocouple,amplifierhardware,micropython,circuitpython
Classifier: Intended Audience :: Developers
Classifier: Topic :: Software Development :: Libraries
Classifier: Topic :: Software Development :: Embedded Systems
Classifier: Topic :: System :: Hardware
Classifier: License :: OSI Approved :: MIT License
Classifier: Programming Language :: Python :: 3
License-File: LICENSE
Requires-Dist: Adafruit-Blinka
Requires-Dist: adafruit-circuitpython-busdevice
Requires-Dist: typing-extensions~=4.0
Provides-Extra: optional
Dynamic: license-file
